mylocale/TR.py
mylocale/__init__.py
mylocale/create.py
mylocale-2025.9.23.dist-info/LICENSE
mylocale-2025.9.23.dist-info/METADATA
mylocale-2025.9.23.dist-info/WHEEL
mylocale-2025.9.23.dist-info/entry_points.txt
mylocale-2025.9.23.dist-info/RECORD
