Metadata-Version: 2.3
Name: mylocale
Version: 2025.9.23
Summary: A simple python library for simple localisation wit CSV files.
License: MIT
Author: tct123
Author-email: 42028373+tct123@users.noreply.github.com
Requires-Python: >=3.8
Classifier: License :: OSI Approved :: MIT License
Classifier: Programming Language :: Python :: 3
Classifier: Programming Language :: Python :: 3.8
Classifier: Programming Language :: Python :: 3.9
Classifier: Programming Language :: Python :: 3.10
Classifier: Programming Language :: Python :: 3.11
Classifier: Programming Language :: Python :: 3.12
Classifier: Programming Language :: Python :: 3.13
Project-URL: Documentation, https://mylocale.readthedocs.io
Project-URL: Homepage, https://github.com/tct123/mylocale
Project-URL: Repository, https://github.com/tct123/mylocale
